database.py
setup.py
simple_database.egg-info/PKG-INFO
simple_database.egg-info/SOURCES.txt
simple_database.egg-info/dependency_links.txt
simple_database.egg-info/requires.txt
simple_database.egg-info/top_level.txt