Metadata-Version: 1.1
Name: simple-database
Version: 1.0.1
Summary: A simple database module that made by module shelve.
Home-page: https://github.com/qfcy/Python/tree/main/Terminal/database.py
Author: qfcy
Author-email: 3076711200@qq.com
License: UNKNOWN
Keywords: database,data
Platform: UNKNOWN
Classifier: Programming Language :: Python
Classifier: Natural Language :: Chinese (Simplified)
Classifier: Topic :: Database
